<shapes>
  <poly id="1" type="building" color="0.10,0.10,0.10" fill="1" layer="4" shape="35,35 35,85 280,85 280,35"/>
  <poly id="2" type="building" color="0.10,0.10,0.10" fill="1" layer="4" shape="35,115 35,165 280,165 280,115"/>
  <poly id="3" type="building" color="0.10,0.10,0.10" fill="1" layer="4" shape="35,195 35,245 280,245 280,195"/>
  <poly id="4" type="building" color="0.10,0.10,0.10" fill="1" layer="4" shape="35,275 35,325 280,325 280,275"/>
  <poly id="5" type="building" color="0.10,0.10,0.10" fill="1" layer="4" shape="35,355 35,405 280,405 280,355"/>
  <poly id="6" type="building" color="0.10,0.10,0.10" fill="1" layer="4" shape="35,435 35,485 280,485 280,435"/>
  <poly id="7" type="building" color="0.10,0.10,0.10" fill="1" layer="4" shape="35,515 35,565 280,565 280,515"/>
  <poly id="8" type="building" color="0.10,0.10,0.10" fill="1" layer="4" shape="35,595 35,645 280,645 280,595"/>
  <poly id="9" type="building" color="0.10,0.10,0.10" fill="1" layer="4" shape="35,675 35,725 280,725 280,675"/>
  <poly id="10" type="building" color="0.10,0.10,0.10" fill="1" layer="4" shape="310,35 310,85 555,85 555,35"/>
  <poly id="11" type="building" color="0.10,0.10,0.10" fill="1" layer="4" shape="310,115 310,165 555,165 555,115"/>
  <poly id="12" type="building" color="0.10,0.10,0.10" fill="1" layer="4" shape="310,195 310,245 555,245 555,195"/>
  <poly id="13" type="building" color="0.10,0.10,0.10" fill="1" layer="4" shape="310,275 310,325 555,325 555,275"/>
  <poly id="14" type="building" color="0.10,0.10,0.10" fill="1" layer="4" shape="310,355 310,405 555,405 555,355"/>
  <poly id="15" type="building" color="0.10,0.10,0.10" fill="1" layer="4" shape="310,435 310,485 555,485 555,435"/>
  <poly id="16" type="building" color="0.10,0.10,0.10" fill="1" layer="4" shape="310,515 310,565 555,565 555,515"/>
  <poly id="17" type="building" color="0.10,0.10,0.10" fill="1" layer="4" shape="310,595 310,645 555,645 555,595"/>
  <poly id="18" type="building" color="0.10,0.10,0.10" fill="1" layer="4" shape="310,675 310,725 555,725 555,675"/>
  <poly id="19" type="building" color="0.10,0.10,0.10" fill="1" layer="4" shape="585,35 585,85 830,85 830,35"/>
  <poly id="20" type="building" color="0.10,0.10,0.10" fill="1" layer="4" shape="585,115 585,165 830,165 830,115"/>
  <poly id="21" type="building" color="0.10,0.10,0.10" fill="1" layer="4" shape="585,195 585,245 830,245 830,195"/>
  <poly id="22" type="building" color="0.10,0.10,0.10" fill="1" layer="4" shape="585,275 585,325 830,325 830,275"/>
  <poly id="23" type="building" color="0.10,0.10,0.10" fill="1" layer="4" shape="585,355 585,405 830,405 830,355"/>
  <poly id="24" type="building" color="0.10,0.10,0.10" fill="1" layer="4" shape="585,435 585,485 830,485 830,435"/>
  <poly id="25" type="building" color="0.10,0.10,0.10" fill="1" layer="4" shape="585,515 585,565 830,565 830,515"/>
  <poly id="26" type="building" color="0.10,0.10,0.10" fill="1" layer="4" shape="585,595 585,645 830,645 830,595"/>
  <poly id="27" type="building" color="0.10,0.10,0.10" fill="1" layer="4" shape="585,675 585,725 830,725 830,675"/>
  <poly id="28" type="building" color="0.10,0.10,0.10" fill="1" layer="4" shape="860,35 860,85 1105,85 1105,35"/>
  <poly id="29" type="building" color="0.10,0.10,0.10" fill="1" layer="4" shape="860,115 860,165 1105,165 1105,115"/>
  <poly id="30" type="building" color="0.10,0.10,0.10" fill="1" layer="4" shape="860,195 860,245 1105,245 1105,195"/>
  <poly id="31" type="building" color="0.10,0.10,0.10" fill="1" layer="4" shape="860,275 860,325 1105,325 1105,275"/>
  <poly id="32" type="building" color="0.10,0.10,0.10" fill="1" layer="4" shape="860,355 860,405 1105,405 1105,355"/>
  <poly id="33" type="building" color="0.10,0.10,0.10" fill="1" layer="4" shape="860,435 860,485 1105,485 1105,435"/>
  <poly id="34" type="building" color="0.10,0.10,0.10" fill="1" layer="4" shape="860,515 860,565 1105,565 1105,515"/>
  <poly id="35" type="building" color="0.10,0.10,0.10" fill="1" layer="4" shape="860,595 860,645 1105,645 1105,595"/>
  <poly id="36" type="building" color="0.10,0.10,0.10" fill="1" layer="4" shape="860,675 860,725 1105,725 1105,675"/>
</shapes>
